{
  "hash": "d4cf3d6b37314a0ac3f7b414b3161aaa",
  "result": {
    "markdown": "---\ntitle: \"Status\"\neditor: visual\n---\n\n::: {.cell}\n\n:::\n\n\n## Workflow Status\n\n\n::: {.cell}\n::: {.cell-output-display}\n```{=html}\n<div class=\"reactable html-widget html-fill-item-overflow-hidden html-fill-item\" id=\"htmlwidget-4a526d0fba7c1634a9a8\" style=\"width:auto;height:auto;\"></div>\n<script type=\"application/json\" data-for=\"htmlwidget-4a526d0fba7c1634a9a8\">{\"x\":{\"tag\":{\"name\":\"Reactable\",\"attribs\":{\"data\":{\"hc_names\":[\"Lake: ALEX GLM\",\"Lake: BVRE GLM\",\"Dashboard: Build\",\"Lake: CRAM GLM\",\"NOAA: GEFS today (16-day)\",\"Lake: SUGG GLM\",\"NOAA: GEFS (35-day)\",\"Lake: TOOK GLM\",\"Lake: PRLA GLM\",\"Lake: CCRE GLM\",\"Lake: SUNP GLM\",\"Lake: BARC GLM\",\"Lake: FCRE GLM\",\"Lake: Submit NEON forecasts\",\"S3: Sync S3 to OSN\",\"Lake: LIRO GLM\",\"Lake: PRPO GLM\",\"Temporary: LER sims\"],\"hc_status\":[\"up\",\"up\",\"up\",\"up\",\"down\",\"up\",\"up\",\"up\",\"up\",\"up\",\"up\",\"up\",\"up\",\"up\",\"up\",\"up\",\"up\",\"down\"],\"hc_latest\":[\"2023-06-16 11:14:27\",\"2023-06-16 11:16:43\",\"2023-06-16 12:58:35\",\"2023-06-16 11:24:48\",\"2023-05-24 07:08:36\",\"2023-06-16 11:39:40\",\"2023-06-16 04:06:32\",\"2023-06-16 11:47:40\",\"2023-06-16 11:42:44\",\"2023-06-16 11:25:05\",\"2023-06-16 11:16:05\",\"2023-06-16 11:22:01\",\"2023-06-16 11:28:38\",\"2023-06-16 20:14:57\",\"2023-06-16 07:01:42\",\"2023-06-16 11:25:23\",\"2023-06-16 11:52:31\",\"2023-05-30 15:44:26\"]},\"columns\":[{\"id\":\"hc_names\",\"name\":\"Process Name\",\"type\":\"character\",\"align\":\"left\"},{\"id\":\"hc_status\",\"name\":\"Status\",\"type\":\"character\",\"align\":\"left\"},{\"id\":\"hc_latest\",\"name\":\"Updated (UTC)\",\"type\":\"character\",\"align\":\"left\"}],\"filterable\":true,\"defaultPageSize\":10,\"highlight\":true,\"dataKey\":\"2a14a5ccc313418560919328ce2d9671\"},\"children\":[]},\"class\":\"reactR_markup\"},\"evals\":[],\"jsHooks\":[]}</script>\n```\n:::\n:::\n",
    "supporting": [],
    "filters": [
      "rmarkdown/pagebreak.lua"
    ],
    "includes": {
      "include-in-header": [
        "<script src=\"site_libs/core-js-2.5.3/shim.min.js\"></script>\n<script src=\"site_libs/react-17.0.0/react.min.js\"></script>\n<script src=\"site_libs/react-17.0.0/react-dom.min.js\"></script>\n<script src=\"site_libs/reactwidget-1.0.0/react-tools.js\"></script>\n<script src=\"site_libs/htmlwidgets-1.6.2/htmlwidgets.js\"></script>\n<link href=\"site_libs/reactable-0.4.4/reactable.css\" rel=\"stylesheet\" />\n<script src=\"site_libs/reactable-binding-0.4.4/reactable.js\"></script>\n"
      ]
    },
    "engineDependencies": {},
    "preserve": {},
    "postProcess": true
  }
}